README.md
setup.py
androbane/__init__.py
androbane/bruteforcer.py
androbane/ddos.py
androbane/extrafun.py
androbane/hasher.py
androbane/infos.py
androbane/iot.py
androbane/pager.py
androbane/payloads.py
androbane/proxer.py
androbane/vulns.py
androbane/wp.py
androbane.egg-info/PKG-INFO
androbane.egg-info/SOURCES.txt
androbane.egg-info/dependency_links.txt
androbane.egg-info/requires.txt
androbane.egg-info/top_level.txt