Metadata-Version: 2.1
Name: androbane
Version: 1.0.0
Summary: cyber security library
Home-page: https://github.com/AlaBouali/andorbane
Author: AlaBouali
Author-email: trap.leader.123@gmail.com
License: MIT License
Platform: UNKNOWN
Classifier: Programming Language :: Python :: 2.7
Classifier: License :: OSI Approved :: MIT License 
Classifier: Operating System :: Unix
Requires-Python: >=2.7
